{
  "project_info": {
    "project_number": "846998202362",
    "project_id": "ducis-learning",
    "storage_bucket": "ducis-learning.appspot.com"
  },
  "client": [
    {
      "client_info": {
        "mobilesdk_app_id": "1:846998202362:android:5d5bd80a2d0d9eca89e643",
        "android_client_info": {
          "package_name": "com.ducislanguage.mobile"
        }
      },
      "oauth_client": [
        {
          "client_id": "846998202362-qe4jas31oh1quos2a24mfhmmh5slu26i.apps.googleusercontent.com",
          "client_type": 1,
          "android_info": {
            "package_name": "com.ducislanguage.mobile",
            "certificate_hash": "618db0c3e5fe5b398bddb9efac954bed43d2129b"
          }
        },
        {
          "client_id": "846998202362-1u1kutnnqk7hl4s6t3flfram5u24tdqc.apps.googleusercontent.com",
          "client_type": 3
        }
      ],
      "api_key": [
        {
          "current_key": "AIzaSyB3mkiJGEO4HTolwuRfKnT85ZMT0yz-UMg"
        }
      ],
      "services": {
        "appinvite_service": {
          "other_platform_oauth_client": [
            {
              "client_id": "846998202362-1u1kutnnqk7hl4s6t3flfram5u24tdqc.apps.googleusercontent.com",
              "client_type": 3
            }
          ]
        }
      }
    }
  ],
  "configuration_version": "1"
}